textaur/__init__.py
textaur/cli/__init__.py
textaur/cli/main.py
textaur/core/__init__.py
textaur/core/ai_linter.py
textaur/core/context.py
textaur/core/pipeline.py
textaur/core/strutil.py
textaur/core/textifier.py
textaur/prompts/lint_generic_text.txt
textaur/prompts/lint_screenplay.txt
textaur-0.1.0.dist-info/licenses/LICENSE
textaur-0.1.0.dist-info/METADATA
textaur-0.1.0.dist-info/WHEEL
textaur-0.1.0.dist-info/entry_points.txt
textaur-0.1.0.dist-info/top_level.txt
textaur-0.1.0.dist-info/RECORD
