Metadata-Version: 2.4
Name: textaur
Version: 0.1.0
Summary: LLM-powered text linter
Author-email: John Hudson <jh@ingratexr.com>
License-Expression: MIT
Project-URL: Homepage, https://github.com/ingratexr/textaur
Requires-Python: >=3.13
License-File: LICENSE
Requires-Dist: click>=8.2.1
Requires-Dist: openai>=1.99.9
Requires-Dist: python-dotenv>=1.1.1
Requires-Dist: pdf2image>=1.17.0
Requires-Dist: pytesseract>=0.3.13
Requires-Dist: pdfminer.six>=20250506
Dynamic: license-file
